odoo/addons/web_refresher/README.rst
odoo/addons/web_refresher/__init__.py
odoo/addons/web_refresher/__manifest__.py
odoo/addons/web_refresher/i18n/ca.po
odoo/addons/web_refresher/i18n/es.po
odoo/addons/web_refresher/i18n/pt_BR.po
odoo/addons/web_refresher/i18n/web_refresher.pot
odoo/addons/web_refresher/images/refresh.png
odoo/addons/web_refresher/readme/CONTRIBUTORS.rst
odoo/addons/web_refresher/readme/DESCRIPTION.rst
odoo/addons/web_refresher/static/description/icon.png
odoo/addons/web_refresher/static/description/index.html
odoo/addons/web_refresher/static/src/js/refresher.js
odoo/addons/web_refresher/templates/assets.xml
odoo12_addon_web_refresher-12.0.1.0.0.99.dev10.dist-info/METADATA
odoo12_addon_web_refresher-12.0.1.0.0.99.dev10.dist-info/WHEEL
odoo12_addon_web_refresher-12.0.1.0.0.99.dev10.dist-info/top_level.txt
odoo12_addon_web_refresher-12.0.1.0.0.99.dev10.dist-info/RECORD
